openwakewordlistener/__init__.py
openwakewordlistener/__main__.py
openwakewordlistener/audiodata.py
openwakewordlistener/wakeword_listener.py
openwakewordlistener-0.0.6.dist-info/METADATA
openwakewordlistener-0.0.6.dist-info/WHEEL
openwakewordlistener-0.0.6.dist-info/licenses/LICENSE
openwakewordlistener-0.0.6.dist-info/RECORD
