Metadata-Version: 2.4
Name: openwakewordlistener
Version: 0.0.6
Summary: A wake word detection system for Rhasspy
Project-URL: Homepage, https://github.com/erikjber/OpenWakeWordListener
Project-URL: Issues, https://github.com/erikjber/OpenWakeWordListener/issues
Author-email: Erik Berglund <erik.berglund@gmail.com>
License-Expression: CC-BY-SA-4.0
License-File: LICENSE
Classifier: Operating System :: OS Independent
Classifier: Programming Language :: Python :: 3
Requires-Python: >=3.9
Requires-Dist: openai-whisper
Requires-Dist: paho-mqtt
Requires-Dist: silero-vad
Requires-Dist: torch
